deprecated_params/__init__.py
deprecated_params-0.3.0.dist-info/licenses/LICENSE
deprecated_params-0.3.0.dist-info/METADATA
deprecated_params-0.3.0.dist-info/WHEEL
deprecated_params-0.3.0.dist-info/top_level.txt
deprecated_params-0.3.0.dist-info/RECORD
