Metadata-Version: 2.4
Name: deprecated-params
Version: 0.3.0
Summary: A Wrapper for functions, class objects and methods for deprecating keyword parameters
Author-email: Vizonex <VizonexBusiness@gmail.com>
License-Expression: MIT
Project-URL: homepage, https://github.com/Vizonex/deprecated-params
Project-URL: repository, https://github.com/Vizonex/deprecated-params.git
Requires-Python: >=3.10
License-File: LICENSE
Requires-Dist: typing-extensions; python_version < "3.13"
Dynamic: license-file
